{
  "name": "TaskFlow API",
  "version": "1",
  "items": [
    {
      "type": "http",
      "name": "Register",
      "filename": "Register.bru",
      "seq": 1,
      "settings": {
        "encodeUrl": true
      },
      "tags": [],
      "request": {
        "url": "http://localhost:5000/auth/register",
        "method": "POST",
        "headers": [],
        "params": [],
        "body": {
          "mode": "json",
          "json": "{\n  \"name\": \"Sejal\",\n  \"email\": \"sejalaa677@example.com\",\n  \"password\": \"1234567\"\n}",
          "formUrlEncoded": [],
          "multipartForm": [],
          "file": []
        },
        "script": {},
        "vars": {},
        "assertions": [],
        "tests": "",
        "docs": "",
        "auth": {
          "mode": "inherit"
        }
      }
    },
    {
      "type": "http",
      "name": "Login",
      "filename": "Login.bru",
      "seq": 2,
      "settings": {
        "encodeUrl": true
      },
      "tags": [],
      "request": {
        "url": "http://localhost:5000/auth/login",
        "method": "POST",
        "headers": [],
        "params": [],
        "body": {
          "mode": "none",
          "formUrlEncoded": [],
          "multipartForm": [],
          "file": []
        },
        "script": {},
        "vars": {},
        "assertions": [],
        "tests": "",
        "docs": "",
        "auth": {
          "mode": "inherit"
        }
      }
    },
    {
      "type": "http",
      "name": "Create Projects",
      "filename": "Create Projects.bru",
      "seq": 3,
      "settings": {
        "encodeUrl": true
      },
      "tags": [],
      "request": {
        "url": "http://localhost:5000/projects",
        "method": "POST",
        "headers": [],
        "params": [],
        "body": {
          "mode": "none",
          "formUrlEncoded": [],
          "multipartForm": [],
          "file": []
        },
        "script": {},
        "vars": {},
        "assertions": [],
        "tests": "",
        "docs": "",
        "auth": {
          "mode": "inherit"
        }
      }
    },
    {
      "type": "http",
      "name": "Create Task",
      "filename": "Create Task.bru",
      "seq": 4,
      "settings": {
        "encodeUrl": true
      },
      "tags": [],
      "request": {
        "url": "http://localhost:5000/tasks",
        "method": "POST",
        "headers": [],
        "params": [],
        "body": {
          "mode": "none",
          "formUrlEncoded": [],
          "multipartForm": [],
          "file": []
        },
        "script": {},
        "vars": {},
        "assertions": [],
        "tests": "",
        "docs": "",
        "auth": {
          "mode": "inherit"
        }
      }
    },
    {
      "type": "http",
      "name": "Get Projects",
      "filename": "Get Projects.bru",
      "seq": 5,
      "settings": {
        "encodeUrl": true
      },
      "tags": [],
      "request": {
        "url": "http://localhost:5000/projects",
        "method": "GET",
        "headers": [],
        "params": [],
        "body": {
          "mode": "none",
          "formUrlEncoded": [],
          "multipartForm": [],
          "file": []
        },
        "script": {},
        "vars": {},
        "assertions": [],
        "tests": "",
        "docs": "",
        "auth": {
          "mode": "inherit"
        }
      }
    },
    {
      "type": "http",
      "name": "Get Tasks",
      "filename": "Get Tasks.bru",
      "seq": 6,
      "settings": {
        "encodeUrl": true
      },
      "tags": [],
      "request": {
        "url": "http://localhost:5000/tasks",
        "method": "GET",
        "headers": [],
        "params": [],
        "body": {
          "mode": "none",
          "formUrlEncoded": [],
          "multipartForm": [],
          "file": []
        },
        "script": {},
        "vars": {},
        "assertions": [],
        "tests": "",
        "docs": "",
        "auth": {
          "mode": "inherit"
        }
      }
    }
  ],
  "environments": [],
  "brunoConfig": {
    "version": "1",
    "name": "TaskFlow API",
    "type": "collection",
    "ignore": [
      "node_modules",
      ".git"
    ],
    "size": 0,
    "filesCount": 0
  }
}